panda3d_sprite/__init__.py
panda3d_sprite/sprite.py
panda3d_sprite-1.1.0.dist-info/LICENSE
panda3d_sprite-1.1.0.dist-info/METADATA
panda3d_sprite-1.1.0.dist-info/WHEEL
panda3d_sprite-1.1.0.dist-info/top_level.txt
panda3d_sprite-1.1.0.dist-info/RECORD
