Metadata-Version: 2.1
Name: panda3d_sprite
Version: 1.1.0
Summary: Panda3D module provides spritesheet capabilities to the Panda3D game engine
Home-page: https://github.com/NxtStudios/p3d-prite
Author: Jordan Maxwell
Maintainer: Jordan Maxwell
License: MIT
Classifier: Programming Language :: Python :: 3
License-File: LICENSE
